<?xml version="1.0" encoding="UTF-8"?>
<!DOCTYPE mapper PUBLIC "-//mybatis.org//DTD Mapper 3.0//EN" "http://mybatis.org/dtd/mybatis-3-mapper.dtd">
<mapper namespace="org.example.lab1.mybatis.dao.ClassesMapper">
  <resultMap id="BaseResultMap" type="org.example.lab1.mybatis.model.Classes">
    <!--
      WARNING - @mbg.generated
      This element is automatically generated by MyBatis Generator, do not modify.
      This element was generated on Mon Apr 29 00:19:48 EEST 2024.
    -->
    <id column="ID" jdbcType="INTEGER" property="id" />
    <result column="TITLE" jdbcType="VARCHAR" property="title" />
  </resultMap>
  <delete id="deleteByPrimaryKey" parameterType="java.lang.Integer">
    <!--
      WARNING - @mbg.generated
      This element is automatically generated by MyBatis Generator, do not modify.
      This element was generated on Mon Apr 29 00:19:48 EEST 2024.
    -->
    delete from PUBLIC.CLASSES
    where ID = #{id,jdbcType=INTEGER}
  </delete>
  <insert id="insert" keyColumn="ID" keyProperty="id" parameterType="org.example.lab1.mybatis.model.Classes" useGeneratedKeys="true">
    <!--
      WARNING - @mbg.generated
      This element is automatically generated by MyBatis Generator, do not modify.
      This element was generated on Mon Apr 29 00:19:48 EEST 2024.
    -->
    insert into PUBLIC.CLASSES (TITLE)
    values (#{title,jdbcType=VARCHAR})
  </insert>
  <update id="updateByPrimaryKey" parameterType="org.example.lab1.mybatis.model.Classes">
    <!--
      WARNING - @mbg.generated
      This element is automatically generated by MyBatis Generator, do not modify.
      This element was generated on Mon Apr 29 00:19:48 EEST 2024.
    -->
    update PUBLIC.CLASSES
    set TITLE = #{title,jdbcType=VARCHAR}
    where ID = #{id,jdbcType=INTEGER}
  </update>
  <select id="selectByPrimaryKey" parameterType="java.lang.Integer" resultMap="BaseResultMap">
    <!--
      WARNING - @mbg.generated
      This element is automatically generated by MyBatis Generator, do not modify.
      This element was generated on Mon Apr 29 00:19:48 EEST 2024.
    -->
    select ID, TITLE
    from PUBLIC.CLASSES
    where ID = #{id,jdbcType=INTEGER}
  </select>
  <select id="selectAll" resultMap="BaseResultMap">
    <!--
      WARNING - @mbg.generated
      This element is automatically generated by MyBatis Generator, do not modify.
      This element was generated on Mon Apr 29 00:19:48 EEST 2024.
    -->
    select ID, TITLE
    from PUBLIC.CLASSES
  </select>
</mapper>